appsyncclient/__init__.py
appsyncclient/awssigner.py
appsyncclient/index.py
appsync_client-0.0.13.dist-info/LICENSE
appsync_client-0.0.13.dist-info/METADATA
appsync_client-0.0.13.dist-info/WHEEL
appsync_client-0.0.13.dist-info/top_level.txt
appsync_client-0.0.13.dist-info/RECORD
