Metadata-Version: 2.1
Name: appsync-client
Version: 0.0.13
Summary: Appsync python client for consuming the graphql endpoint
Home-page: https://github.com/vasudevan-palani/appsync-client
Author: Vasudevan Palani
Author-email: vasudevan.palani@gmail.com
License: TBD
Platform: UNKNOWN
